pgworkload_odbc/__init__.py
pgworkload_odbc/cli/main.py
pgworkload_odbc/models/run.py
pgworkload_odbc/models/util.py
pgworkload_odbc/utils/util.py
pgworkload_odbc-0.1.0.dist-info/LICENSE
pgworkload_odbc-0.1.0.dist-info/METADATA
pgworkload_odbc-0.1.0.dist-info/WHEEL
pgworkload_odbc-0.1.0.dist-info/entry_points.txt
pgworkload_odbc-0.1.0.dist-info/RECORD
