Metadata-Version: 2.1
Name: pgworkload-odbc
Version: 0.1.0
Summary: pgworkload's little pyodbc brother
Home-page: https://github.com/fabiog1901/pgworkload_odbc
License: GPLv3+
Author: Fabio Ghirardello
Requires-Python: >=3.8,<4.0
Classifier: License :: OSI Approved :: GNU General Public License v3 or later (GPLv3+)
Classifier: License :: Other/Proprietary License
Classifier: Operating System :: OS Independent
Classifier: Programming Language :: Python :: 3
Classifier: Programming Language :: Python :: 3.8
Classifier: Programming Language :: Python :: 3.9
Classifier: Programming Language :: Python :: 3.10
Classifier: Programming Language :: Python :: 3.11
Classifier: Programming Language :: Python :: 3
Requires-Dist: numpy (>=1.23.5,<2.0.0)
Requires-Dist: prometheus-client (>=0.15.0,<0.16.0)
Requires-Dist: pyodbc (>=4.0.39,<5.0.0)
Requires-Dist: pyyaml (>=6.0,<7.0)
Requires-Dist: tabulate (>=0.9.0,<0.10.0)
Requires-Dist: typer[all] (>=0.7.0,<0.8.0)
Project-URL: Repository, https://github.com/fabiog1901/pgworkload_odbc
